ai_img_gen/__init__.py
ai_img_gen-0.1.3.dist-info/LICENSE
ai_img_gen-0.1.3.dist-info/WHEEL
ai_img_gen-0.1.3.dist-info/METADATA
ai_img_gen-0.1.3.dist-info/RECORD
