Metadata-Version: 2.1
Name: ai-img-gen
Version: 0.1.3
Summary: 
Author: Neriah "BJ" Ato
Author-email: n.d.ato@ieee.org
Requires-Python: >=3.9,<4.0
Classifier: Programming Language :: Python :: 3
Classifier: Programming Language :: Python :: 3.9
Classifier: Programming Language :: Python :: 3.10
Classifier: Programming Language :: Python :: 3.11
Requires-Dist: fastapi (>=0.89.1,<0.90.0)
Requires-Dist: openai (>=0.25.0,<0.26.0)
Requires-Dist: python-dotenv (>=0.21.0,<0.22.0)
Requires-Dist: python-multipart (>=0.0.5,<0.0.6)
Requires-Dist: uvicorn (>=0.20.0,<0.21.0)
